Metadata-Version: 1.1
Name: openapi-codec-devin
Version: 1.0.0
Summary: An OpenAPI codec for Core API.
Home-page: https://github.com/waipbmtd/python-openapi-codec
Author: Devin
Author-email: waipbmtd@gmail.com
License: BSD
Platform: UNKNOWN
Classifier: Intended Audience :: Developers
Classifier: License :: OSI Approved :: BSD License
Classifier: Operating System :: OS Independent
Classifier: Programming Language :: Python
Classifier: Programming Language :: Python :: 3
